{
  "Blackvale Corruption": { "entity_type": "Section", "tags": [] },
  "Deepshore Missing Kids": { "entity_type": "Section", "tags": [] },
  "Gods Of Tharoline": { "entity_type": "Section", "tags": [] },
  "Aliases": { "entity_type": "Section", "tags": [] },
  "Fairy Queen Quests": { "entity_type": "Section", "tags": [] },
  "Relationships": { "entity_type": "Section", "tags": [] },
  "Lore Dumps": { "entity_type": "Section", "tags": [] },
  "Backstory": { "entity_type": "Section", "tags": [] },
  "parents": { "entity_type": "Section", "tags": [] },
  "Amarei's vision": { "entity_type": "Section", "tags": [] },
  "Ezemor": { "entity_type": "Location", "tags": ["Region"] },
  "Blackvale": { "entity_type": "Location", "tags": ["Region"] },
  "Deepshore": { "entity_type": "Location", "tags": ["Region"] },
  "Whiteworf": { "entity_type": "Location", "tags": ["Region"] },
  "New Coast": { "entity_type": "Location", "tags": ["Region"] },
  "The Barrel": { "entity_type": "Location", "tags": ["Region"] },
  "Badlands": { "entity_type": "Location", "tags": ["Region"] },
  "Long Sea": { "entity_type": "Location", "tags": ["Region"] },
  "Horetown": { "entity_type": "Location", "tags": ["Region"] },
  "Veros": { "entity_type": "Location", "tags": ["Region"] },
  "Estolen": { "entity_type": "Location", "tags": ["Region"] },
  "Shadowfell": { "entity_type": "Location", "tags": ["Region"] },
  "Tharoline": { "entity_type": "Location", "tags": ["Region"] },
  "Feywild": { "entity_type": "Location", "tags": ["Region"] },
  "Jacaris": { "entity_type": "Location", "tags": ["Region"] },
  "Meijing": { "entity_type": "Location", "tags": ["Region"] },
  "Harthill": { "entity_type": "Location", "tags": ["Region"] },
  "Iron Post": { "entity_type": "Location", "tags": ["Region"] },
  "Library Of Ilios": { "entity_type": "Location", "tags": ["Region"] },
  "Rothstar": { "entity_type": "Organization", "tags": ["Allignment"] },
  "Winking Moon": { "entity_type": "Organization", "tags": ["Allignment"] },
  "The Invaluables": { "entity_type": "Organization", "tags": ["Allignment"] },
  "Crow": { "entity_type": "Organization", "tags": ["Allignment"] },
  "Cursh": { "entity_type": "Organization", "tags": ["Allignment"] },
  "Freedom Fighters": { "entity_type": "Organization", "tags": ["Allignment"] },
  "Elven Sons": { "entity_type": "Organization", "tags": ["Allignment"] },
  "Elven": { "entity_type": "Organization", "tags": ["Allignment"] },
  "Bookeeper'S Alliance": {
    "entity_type": "Organization",
    "tags": ["Allignment"]
  },
  "The Egg": { "entity_type": "Character", "tags": ["Alignment"] },
  "Hendrix": { "entity_type": "Character", "tags": ["Alignment"] },
  "Horonok": { "entity_type": "Character", "tags": ["Alignment"] },
  "Louie": { "entity_type": "Character", "tags": ["Alignment"] },
  "Nelan Voz": { "entity_type": "Character", "tags": ["Alignment"] },
  "Reginald": {
    "entity_type": "Character",
    "tags": ["Alignment"]
  },
  "Tristan Graham": { "entity_type": "Character", "tags": ["Alignment"] },
  "Hilde": { "entity_type": "Character", "tags": ["Alignment"] },
  "Lady Marowin": { "entity_type": "Character", "tags": ["Alignment"] },
  "Ignis": { "entity_type": "Character", "tags": ["Alignment"] },
  "The Architect": { "entity_type": "Character", "tags": ["Alignment"] },
  "Walter Graven": { "entity_type": "Character", "tags": ["Alignment"] },
  "The Accountant": { "entity_type": "Character", "tags": ["Alignment"] },
  "Stephen Hurancamp": { "entity_type": "Character", "tags": ["Alignment"] },
  "Alfred Crush": { "entity_type": "Character", "tags": ["Alignment"] },
  "Beckman": { "entity_type": "Character", "tags": ["Alignment"] },
  "Scrag Beckman": { "entity_type": "Character", "tags": ["Alignment"] },
  "Krenos": { "entity_type": "Character", "tags": ["Alignment"] },
  "Aeredon": { "entity_type": "Character", "tags": ["Alignment"] },
  "Ilios": { "entity_type": "Character", "tags": ["Alignment"] },
  "Tiroth": { "entity_type": "Character", "tags": ["Alignment"] },
  "Ruthos": { "entity_type": "Character", "tags": ["Alignment"] },
  "Jurzod": { "entity_type": "Character", "tags": ["Alignment"] },
  "Drak": { "entity_type": "Character", "tags": ["Alignment"] },
  "Bell": { "entity_type": "Character", "tags": ["Alignment"] },
  "Captain Oreon Pierce": { "entity_type": "Character", "tags": ["Alignment"] },
  "First Lieutenant Alexander Billford": {
    "entity_type": "Character",
    "tags": ["Alignment"]
  },
  "Elegord": { "entity_type": "Character", "tags": ["Alignment"] },
  "Elegan": { "entity_type": "Character", "tags": ["Alignment"] },
  "Luis Fray": { "entity_type": "Character", "tags": ["Alignment"] },
  "Watcher": { "entity_type": "Character", "tags": ["Alignment"] },
  "Builders": { "entity_type": "Character", "tags": ["Alignment"] },
  "Daereth": { "entity_type": "Character", "tags": ["Alignment"] },
  "Eriguin": { "entity_type": "Character", "tags": ["Alignment"] },
  "Illinoth": { "entity_type": "Character", "tags": ["Alignment"] },
  "Dolgrom Ironwood": { "entity_type": "Character", "tags": ["Alignment"] },
  "Crenos": { "entity_type": "Character", "tags": ["Alignment"] },
  "Eradon": { "entity_type": "Character", "tags": ["Alignment"] },
  "Teroth": { "entity_type": "Character", "tags": ["Alignment"] },
  "Ceros": { "entity_type": "Character", "tags": ["Alignment"] },
  "Sigrot": { "entity_type": "Character", "tags": ["Alignment"] },
  "Brandi": { "entity_type": "Character", "tags": ["Alignment"] },
  "Captain Cole": { "entity_type": "Character", "tags": ["Alignment"] },
  "General Takagei": { "entity_type": "Character", "tags": ["Alignment"] },
  "Admiral": { "entity_type": "Character", "tags": ["Alignment"] },
  "Vari": { "entity_type": "Character", "tags": ["Alignment"] },
  "Penny": { "entity_type": "Character", "tags": ["Alignment"] },
  "Granny": { "entity_type": "Character", "tags": ["Alignment"] },
  "Eramus": { "entity_type": "Character", "tags": ["Alignment"] },
  "Red Riding Hood": { "entity_type": "Character", "tags": ["Alignment"] },
  "Amarei": { "entity_type": "Character", "tags": ["Alignment"] },
  "Thrarolinia": { "entity_type": "Character", "tags": ["Alignment"] },
  "Parents": { "entity_type": "Character", "tags": ["Alignment"] },
  "Narissus": { "entity_type": "Character", "tags": ["Alignment"] },
  "King": { "entity_type": "Character", "tags": ["Alignment"] },
  "Tommen": { "entity_type": "Character", "tags": ["Alignment"] },
  "Zadot": { "entity_type": "Character", "tags": ["Alignment"] },
  "Lillith": { "entity_type": "Character", "tags": ["Alignment"] },
  "Otto": { "entity_type": "Character", "tags": ["Alignment"] },
  "Tharolinia": { "entity_type": "Character", "tags": ["Alignment"] },
  "Gulliver": { "entity_type": "Character", "tags": ["Alignment"] },
  "Gerard": { "entity_type": "Character", "tags": ["Alignment"] },
  "Braxar": { "entity_type": "Character", "tags": ["Alignment"] },
  "King Ashflower": { "entity_type": "Character", "tags": ["Alignment"] },
  "Mentira": { "entity_type": "Character", "tags": ["Alignment"] }
}
